README.rst
setup.py
graystruct/__init__.py
graystruct/_version.py
graystruct/encoder.py
graystruct/handler.py
graystruct/rabbitmq.py
graystruct/utils.py
graystruct.egg-info/PKG-INFO
graystruct.egg-info/SOURCES.txt
graystruct.egg-info/dependency_links.txt
graystruct.egg-info/requires.txt
graystruct.egg-info/top_level.txt