Metadata-Version: 1.1
Name: graystruct
Version: 0.1.1
Summary: Integration between structlog and graylog GELF, provided by graypy
Home-page: https://github.com/sjagoe/graystruct
Author: Simon Jagoe
Author-email: simon@simonjagoe.com
License: BSD
Platform: UNKNOWN
Classifier: Development Status :: 1 - Planning
Classifier: Intended Audience :: Developers
Classifier: License :: OSI Approved :: BSD License
Classifier: Programming Language :: Python
Classifier: Topic :: Software Development
Classifier: Topic :: System :: Logging
